{
    "asset": {
        "format": "jpg",
        "id": "daebd3e43ab5c6343b88608d51f95298",
        "name": "20200331_160715.jpg",
        "path": "file:C:/Users/admin/Documents/mlHollf/Images/Jonas%20bilder/20200331_160715.jpg",
        "size": {
            "width": 4128,
            "height": 2322
        },
        "state": 2,
        "type": 1
    },
    "regions": [
        {
            "id": "wOaYNxYeh",
            "type": "RECTANGLE",
            "tags": [
                "beam"
            ],
            "boundingBox": {
                "height": 554.786553402075,
                "width": 2529.0336180949007,
                "left": 744.5212464589235,
                "top": 909.5149209963396
            },
            "points": [
                {
                    "x": 744.5212464589235,
                    "y": 909.5149209963396
                },
                {
                    "x": 3273.5548645538242,
                    "y": 909.5149209963396
                },
                {
                    "x": 3273.5548645538242,
                    "y": 1464.3014743984147
                },
                {
                    "x": 744.5212464589235,
                    "y": 1464.3014743984147
                }
            ]
        },
        {
            "id": "-H_tmZMSy",
            "type": "RECTANGLE",
            "tags": [
                "clockwise",
                "clockwise_left"
            ],
            "boundingBox": {
                "height": 567.253833949966,
                "width": 277.53885778151556,
                "left": 314.180193763279,
                "top": 872.1135549353273
            },
            "points": [
                {
                    "x": 314.180193763279,
                    "y": 872.1135549353273
                },
                {
                    "x": 591.7190515447946,
                    "y": 872.1135549353273
                },
                {
                    "x": 591.7190515447946,
                    "y": 1439.3673888852934
                },
                {
                    "x": 314.180193763279,
                    "y": 1439.3673888852934
                }
            ]
        },
        {
            "id": "Y9AwqndrO",
            "type": "RECTANGLE",
            "tags": [
                "arrow_up"
            ],
            "boundingBox": {
                "height": 760.4939478419772,
                "width": 187.10481586402267,
                "left": 1904.5712475655098,
                "top": 152.13770411958632
            },
            "points": [
                {
                    "x": 1904.5712475655098,
                    "y": 152.13770411958632
                },
                {
                    "x": 2091.6760634295324,
                    "y": 152.13770411958632
                },
                {
                    "x": 2091.6760634295324,
                    "y": 912.6316519615634
                },
                {
                    "x": 1904.5712475655098,
                    "y": 912.6316519615634
                }
            ]
        },
        {
            "id": "-Mf9dNaXr",
            "type": "RECTANGLE",
            "tags": [
                "arrow_up"
            ],
            "boundingBox": {
                "height": 492.4511018279415,
                "width": 190.22318187854108,
                "left": 944.0997642970963,
                "top": 429.5309808206238
            },
            "points": [
                {
                    "x": 944.0997642970963,
                    "y": 429.5309808206238
                },
                {
                    "x": 1134.3229461756373,
                    "y": 429.5309808206238
                },
                {
                    "x": 1134.3229461756373,
                    "y": 921.9820826485653
                },
                {
                    "x": 944.0997642970963,
                    "y": 921.9820826485653
                }
            ]
        },
        {
            "id": "X5uFLCA0u",
            "type": "RECTANGLE",
            "tags": [
                "arrow_up"
            ],
            "boundingBox": {
                "height": 501.8012947236132,
                "width": 227.6442878009915,
                "left": 1165.5070821529746,
                "top": 1442.4841198505171
            },
            "points": [
                {
                    "x": 1165.5070821529746,
                    "y": 1442.4841198505171
                },
                {
                    "x": 1393.151369953966,
                    "y": 1442.4841198505171
                },
                {
                    "x": 1393.151369953966,
                    "y": 1944.2854145741303
                },
                {
                    "x": 1165.5070821529746,
                    "y": 1944.2854145741303
                }
            ]
        },
        {
            "id": "PoXp9Qbum",
            "type": "RECTANGLE",
            "tags": [
                "arrow_up"
            ],
            "boundingBox": {
                "height": 486.2174021061635,
                "width": 143.4469779125354,
                "left": 1708.1110957418555,
                "top": 1442.4841198505171
            },
            "points": [
                {
                    "x": 1708.1110957418555,
                    "y": 1442.4841198505171
                },
                {
                    "x": 1851.558073654391,
                    "y": 1442.4841198505171
                },
                {
                    "x": 1851.558073654391,
                    "y": 1928.7015219566806
                },
                {
                    "x": 1708.1110957418555,
                    "y": 1928.7015219566806
                }
            ]
        },
        {
            "id": "Sw5Y3ImPA",
            "type": "RECTANGLE",
            "tags": [
                "ground"
            ],
            "boundingBox": {
                "height": 1056.5878481256882,
                "width": 299.36789571529744,
                "left": 3239.2521246458923,
                "top": 613.4209612647959
            },
            "points": [
                {
                    "x": 3239.2521246458923,
                    "y": 613.4209612647959
                },
                {
                    "x": 3538.6200203611897,
                    "y": 613.4209612647959
                },
                {
                    "x": 3538.6200203611897,
                    "y": 1670.0088093904842
                },
                {
                    "x": 3239.2521246458923,
                    "y": 1670.0088093904842
                }
            ]
        }
    ],
    "version": "2.1.0"
}