{
    "asset": {
        "format": "jpg",
        "id": "52479e66276060818bcb5f957409e987",
        "name": "a0200322_222024.jpg",
        "path": "file:C:/Users/benja/OneDrive/Desktop/Kand/mlHollf/TrainYourOwnYOLO/Data/Source_Images/training2/a0200322_222024.jpg",
        "size": {
            "width": 4032,
            "height": 3024
        },
        "state": 2,
        "type": 1
    },
    "regions": [
        {
            "id": "oSFLSWfez",
            "type": "RECTANGLE",
            "tags": [
                "beam_thicc"
            ],
            "boundingBox": {
                "height": 403.19997393074686,
                "width": 2426.0338983050847,
                "left": 1031.491525423729,
                "top": 1301.8577053264037
            },
            "points": [
                {
                    "x": 1031.491525423729,
                    "y": 1301.8577053264037
                },
                {
                    "x": 3457.5254237288136,
                    "y": 1301.8577053264037
                },
                {
                    "x": 3457.5254237288136,
                    "y": 1705.0576792571505
                },
                {
                    "x": 1031.491525423729,
                    "y": 1705.0576792571505
                }
            ]
        },
        {
            "id": "lH7-RiR5D",
            "type": "RECTANGLE",
            "tags": [
                "load_up"
            ],
            "boundingBox": {
                "height": 717.5593220338983,
                "width": 1616.217053429555,
                "left": 1513.2813037936971,
                "top": 1588.8813559322034
            },
            "points": [
                {
                    "x": 1513.2813037936971,
                    "y": 1588.8813559322034
                },
                {
                    "x": 3129.4983572232522,
                    "y": 1588.8813559322034
                },
                {
                    "x": 3129.4983572232522,
                    "y": 2306.4406779661017
                },
                {
                    "x": 1513.2813037936971,
                    "y": 2306.4406779661017
                }
            ]
        },
        {
            "id": "IRMkJfTbe",
            "type": "RECTANGLE",
            "tags": [
                "counterclockwise_left"
            ],
            "boundingBox": {
                "height": 775.6474836963719,
                "width": 440.7863624702066,
                "left": 641.9594002416578,
                "top": 1199.3492307501324
            },
            "points": [
                {
                    "x": 641.9594002416578,
                    "y": 1199.3492307501324
                },
                {
                    "x": 1082.7457627118645,
                    "y": 1199.3492307501324
                },
                {
                    "x": 1082.7457627118645,
                    "y": 1974.9967144465043
                },
                {
                    "x": 641.9594002416578,
                    "y": 1974.9967144465043
                }
            ]
        },
        {
            "id": "QmM2VEMzK",
            "type": "RECTANGLE",
            "tags": [
                "arrow_down"
            ],
            "boundingBox": {
                "height": 953.3288005246955,
                "width": 399.78294657044495,
                "left": 1848.1424250198625,
                "top": 447.6203520176775
            },
            "points": [
                {
                    "x": 1848.1424250198625,
                    "y": 447.6203520176775
                },
                {
                    "x": 2247.9253715903073,
                    "y": 447.6203520176775
                },
                {
                    "x": 2247.9253715903073,
                    "y": 1400.949152542373
                },
                {
                    "x": 1848.1424250198625,
                    "y": 1400.949152542373
                }
            ]
        },
        {
            "id": "T6N2QqYN6",
            "type": "RECTANGLE",
            "tags": [
                "arrow_down"
            ],
            "boundingBox": {
                "height": 587.7152803065413,
                "width": 276.77282921742585,
                "left": 2739.9661016949153,
                "top": 779.0643807104078
            },
            "points": [
                {
                    "x": 2739.9661016949153,
                    "y": 779.0643807104078
                },
                {
                    "x": 3016.7389309123414,
                    "y": 779.0643807104078
                },
                {
                    "x": 3016.7389309123414,
                    "y": 1366.7796610169491
                },
                {
                    "x": 2739.9661016949153,
                    "y": 1366.7796610169491
                }
            ]
        },
        {
            "id": "FygXOi3oJ",
            "type": "RECTANGLE",
            "tags": [
                "ground"
            ],
            "boundingBox": {
                "height": 553.5457887811176,
                "width": 153.76271186440678,
                "left": 3402.854550119174,
                "top": 1137.844041727357
            },
            "points": [
                {
                    "x": 3402.854550119174,
                    "y": 1137.844041727357
                },
                {
                    "x": 3556.6172619835806,
                    "y": 1137.844041727357
                },
                {
                    "x": 3556.6172619835806,
                    "y": 1691.3898305084747
                },
                {
                    "x": 3402.854550119174,
                    "y": 1691.3898305084747
                }
            ]
        }
    ],
    "version": "2.1.0"
}