{
    "asset": {
        "format": "jpg",
        "id": "713cfe4f65268df4ebb019f98805c652",
        "name": "20200322_221850.jpg",
        "path": "file:/home/oliv/Documents/mlHollf/TrainYourOwnYOLO/Data/Source_Images/Training_Images/20200322_221850.jpg",
        "size": {
            "width": 4128,
            "height": 2322
        },
        "state": 2,
        "type": 1
    },
    "regions": [
        {
            "id": "jBlzq0xvg",
            "type": "RECTANGLE",
            "tags": [
                "beam_thicc"
            ],
            "boundingBox": {
                "height": 434.3956288343558,
                "width": 1663.734989648033,
                "left": 1521.2919254658384,
                "top": 859.0865797546012
            },
            "points": [
                {
                    "x": 1521.2919254658384,
                    "y": 859.0865797546012
                },
                {
                    "x": 3185.0269151138714,
                    "y": 859.0865797546012
                },
                {
                    "x": 3185.0269151138714,
                    "y": 1293.482208588957
                },
                {
                    "x": 1521.2919254658384,
                    "y": 1293.482208588957
                }
            ]
        },
        {
            "id": "yW-f5rVE0",
            "type": "RECTANGLE",
            "tags": [
                "arrow_up"
            ],
            "boundingBox": {
                "height": 638.1938650306748,
                "width": 142.4430641821946,
                "left": 2481.35817805383,
                "top": 260.77983128834353
            },
            "points": [
                {
                    "x": 2481.35817805383,
                    "y": 260.77983128834353
                },
                {
                    "x": 2623.801242236025,
                    "y": 260.77983128834353
                },
                {
                    "x": 2623.801242236025,
                    "y": 898.9736963190184
                },
                {
                    "x": 2481.35817805383,
                    "y": 898.9736963190184
                }
            ]
        },
        {
            "id": "PuKp5RJuw",
            "type": "RECTANGLE",
            "tags": [
                "load_up"
            ],
            "boundingBox": {
                "height": 589.759509202454,
                "width": 1085.416149068323,
                "left": 2148.041407867495,
                "top": 1246.5614263803682
            },
            "points": [
                {
                    "x": 2148.041407867495,
                    "y": 1246.5614263803682
                },
                {
                    "x": 3233.4575569358176,
                    "y": 1246.5614263803682
                },
                {
                    "x": 3233.4575569358176,
                    "y": 1836.3209355828221
                },
                {
                    "x": 2148.041407867495,
                    "y": 1836.3209355828221
                }
            ]
        },
        {
            "id": "NL2Q_nRkf",
            "type": "RECTANGLE",
            "tags": [
                "clockwise_right"
            ],
            "boundingBox": {
                "height": 669.5337423312883,
                "width": 190.8737060041408,
                "left": 3207.8178053830225,
                "top": 653.9528374233129
            },
            "points": [
                {
                    "x": 3207.8178053830225,
                    "y": 653.9528374233129
                },
                {
                    "x": 3398.6915113871632,
                    "y": 653.9528374233129
                },
                {
                    "x": 3398.6915113871632,
                    "y": 1323.4865797546013
                },
                {
                    "x": 3207.8178053830225,
                    "y": 1323.4865797546013
                }
            ]
        },
        {
            "id": "YY9ADjQIK",
            "type": "RECTANGLE",
            "tags": [
                "roller_support"
            ],
            "boundingBox": {
                "height": 774.9496932515337,
                "width": 546.9813664596273,
                "left": 1136.695652173913,
                "top": 1306.3921012269939
            },
            "points": [
                {
                    "x": 1136.695652173913,
                    "y": 1306.3921012269939
                },
                {
                    "x": 1683.6770186335402,
                    "y": 1306.3921012269939
                },
                {
                    "x": 1683.6770186335402,
                    "y": 2081.3417944785274
                },
                {
                    "x": 1136.695652173913,
                    "y": 2081.3417944785274
                }
            ]
        },
        {
            "id": "XvgcfE1BY",
            "type": "RECTANGLE",
            "tags": [
                "clockwise_left"
            ],
            "boundingBox": {
                "height": 1091.1975460122699,
                "width": 478.6086956521739,
                "left": 931.5776397515527,
                "top": 602.6694018404908
            },
            "points": [
                {
                    "x": 931.5776397515527,
                    "y": 602.6694018404908
                },
                {
                    "x": 1410.1863354037266,
                    "y": 602.6694018404908
                },
                {
                    "x": 1410.1863354037266,
                    "y": 1693.8669478527606
                },
                {
                    "x": 931.5776397515527,
                    "y": 1693.8669478527606
                }
            ]
        },
        {
            "id": "00OLxnXhl",
            "type": "RECTANGLE",
            "tags": [
                "ground"
            ],
            "boundingBox": {
                "height": 219.3791411042945,
                "width": 749.2505175983437,
                "left": 1022.7412008281573,
                "top": 2052.8509969325155
            },
            "points": [
                {
                    "x": 1022.7412008281573,
                    "y": 2052.8509969325155
                },
                {
                    "x": 1771.991718426501,
                    "y": 2052.8509969325155
                },
                {
                    "x": 1771.991718426501,
                    "y": 2272.23013803681
                },
                {
                    "x": 1022.7412008281573,
                    "y": 2272.23013803681
                }
            ]
        }
    ],
    "version": "2.1.0"
}