{
    "asset": {
        "format": "jpg",
        "id": "837a0ec3f63ff9ba8c6cbaa3a78e6174",
        "name": "20200322_221758.jpg",
        "path": "file:/home/oliv/Documents/mlHollf/TrainYourOwnYOLO/Data/Source_Images/Training_Images/20200322_221758.jpg",
        "size": {
            "width": 4128,
            "height": 2322
        },
        "state": 2,
        "type": 1
    },
    "regions": [
        {
            "id": "YXTRgf242",
            "type": "RECTANGLE",
            "tags": [
                "ground"
            ],
            "boundingBox": {
                "height": 190.8883435582822,
                "width": 700.8198757763975,
                "left": 726.4596273291925,
                "top": 505.8006901840491
            },
            "points": [
                {
                    "x": 726.4596273291925,
                    "y": 505.8006901840491
                },
                {
                    "x": 1427.27950310559,
                    "y": 505.8006901840491
                },
                {
                    "x": 1427.27950310559,
                    "y": 696.6890337423313
                },
                {
                    "x": 726.4596273291925,
                    "y": 696.6890337423313
                }
            ]
        },
        {
            "id": "RFAWIPFew",
            "type": "RECTANGLE",
            "tags": [
                "ground"
            ],
            "boundingBox": {
                "height": 170.94478527607362,
                "width": 658.0869565217391,
                "left": 660.935817805383,
                "top": 10.060812883435583
            },
            "points": [
                {
                    "x": 660.935817805383,
                    "y": 10.060812883435583
                },
                {
                    "x": 1319.022774327122,
                    "y": 10.060812883435583
                },
                {
                    "x": 1319.022774327122,
                    "y": 181.0055981595092
                },
                {
                    "x": 660.935817805383,
                    "y": 181.0055981595092
                }
            ]
        },
        {
            "id": "-i3Kvt2xS",
            "type": "RECTANGLE",
            "tags": [
                "ground"
            ],
            "boundingBox": {
                "height": 222.2282208588957,
                "width": 1048.3809523809523,
                "left": 1558.327122153209,
                "top": 1651.1307515337423
            },
            "points": [
                {
                    "x": 1558.327122153209,
                    "y": 1651.1307515337423
                },
                {
                    "x": 2606.7080745341614,
                    "y": 1651.1307515337423
                },
                {
                    "x": 2606.7080745341614,
                    "y": 1873.358972392638
                },
                {
                    "x": 1558.327122153209,
                    "y": 1873.358972392638
                }
            ]
        },
        {
            "id": "csD5et5Y3",
            "type": "RECTANGLE",
            "tags": [
                "roller_support"
            ],
            "boundingBox": {
                "height": 398.87116564417175,
                "width": 376.0496894409938,
                "left": 1908.7370600414079,
                "top": 1275.0522239263803
            },
            "points": [
                {
                    "x": 1908.7370600414079,
                    "y": 1275.0522239263803
                },
                {
                    "x": 2284.786749482402,
                    "y": 1275.0522239263803
                },
                {
                    "x": 2284.786749482402,
                    "y": 1673.9233895705522
                },
                {
                    "x": 1908.7370600414079,
                    "y": 1673.9233895705522
                }
            ]
        },
        {
            "id": "005gf7m9e",
            "type": "RECTANGLE",
            "tags": [
                "roller_support"
            ],
            "boundingBox": {
                "height": 461.55092024539874,
                "width": 418.7826086956522,
                "left": 769.1925465838509,
                "top": 668.198236196319
            },
            "points": [
                {
                    "x": 769.1925465838509,
                    "y": 668.198236196319
                },
                {
                    "x": 1187.975155279503,
                    "y": 668.198236196319
                },
                {
                    "x": 1187.975155279503,
                    "y": 1129.7491564417178
                },
                {
                    "x": 769.1925465838509,
                    "y": 1129.7491564417178
                }
            ]
        },
        {
            "id": "Wtilx0_Mi",
            "type": "RECTANGLE",
            "tags": [
                "counterclockwise_left"
            ],
            "boundingBox": {
                "height": 604.0049079754601,
                "width": 245.00207039337474,
                "left": 595.4120082815734,
                "top": 933.1626533742332
            },
            "points": [
                {
                    "x": 595.4120082815734,
                    "y": 933.1626533742332
                },
                {
                    "x": 840.4140786749482,
                    "y": 933.1626533742332
                },
                {
                    "x": 840.4140786749482,
                    "y": 1537.1675613496932
                },
                {
                    "x": 595.4120082815734,
                    "y": 1537.1675613496932
                }
            ]
        },
        {
            "id": "BOLdudeKm",
            "type": "RECTANGLE",
            "tags": [
                "beam_thicc"
            ],
            "boundingBox": {
                "height": 151.00122699386503,
                "width": 1281.9875776397514,
                "left": 874.6004140786749,
                "top": 1118.3528374233128
            },
            "points": [
                {
                    "x": 874.6004140786749,
                    "y": 1118.3528374233128
                },
                {
                    "x": 2156.5879917184266,
                    "y": 1118.3528374233128
                },
                {
                    "x": 2156.5879917184266,
                    "y": 1269.3540644171778
                },
                {
                    "x": 874.6004140786749,
                    "y": 1269.3540644171778
                }
            ]
        },
        {
            "id": "h6Zj2srO-",
            "type": "RECTANGLE",
            "tags": [
                "arrow_left"
            ],
            "boundingBox": {
                "height": 162.39754601226994,
                "width": 646.6915113871636,
                "left": 2148.041407867495,
                "top": 1129.7491564417178
            },
            "points": [
                {
                    "x": 2148.041407867495,
                    "y": 1129.7491564417178
                },
                {
                    "x": 2794.732919254658,
                    "y": 1129.7491564417178
                },
                {
                    "x": 2794.732919254658,
                    "y": 1292.1467024539877
                },
                {
                    "x": 2148.041407867495,
                    "y": 1292.1467024539877
                }
            ]
        }
    ],
    "version": "2.1.0"
}