{
    "asset": {
        "format": "jpg",
        "id": "909cbca48078cecb80bd37a17cc4216c",
        "name": "20200421_114403.jpg",
        "path": "file:C:/Users/tobia/Desktop/Kandidat/mlHollf/TrainYourOwnYOLO/Data/Source_Images/Training_Images/20200421_114403.jpg",
        "size": {
            "width": 4032,
            "height": 3024
        },
        "state": 2,
        "type": 1
    },
    "regions": [
        {
            "id": "2eRZiykrF",
            "type": "RECTANGLE",
            "tags": [
                "beam"
            ],
            "boundingBox": {
                "height": 382.57420666383047,
                "width": 1663.3663873955754,
                "left": 1284.1188626431003,
                "top": 1363.9604468015161
            },
            "points": [
                {
                    "x": 1284.1188626431003,
                    "y": 1363.9604468015161
                },
                {
                    "x": 2947.4852500386755,
                    "y": 1363.9604468015161
                },
                {
                    "x": 2947.4852500386755,
                    "y": 1746.5346534653465
                },
                {
                    "x": 1284.1188626431003,
                    "y": 1746.5346534653465
                }
            ]
        },
        {
            "id": "dE1w_3OkG",
            "type": "RECTANGLE",
            "tags": [
                "counterclockwise",
                "counterclockwise_left"
            ],
            "boundingBox": {
                "height": 469.0693069306931,
                "width": 212.91084032719678,
                "left": 944.7921299698329,
                "top": 1340.673368850557
            },
            "points": [
                {
                    "x": 944.7921299698329,
                    "y": 1340.673368850557
                },
                {
                    "x": 1157.7029702970297,
                    "y": 1340.673368850557
                },
                {
                    "x": 1157.7029702970297,
                    "y": 1809.74267578125
                },
                {
                    "x": 944.7921299698329,
                    "y": 1809.74267578125
                }
            ]
        },
        {
            "id": "Fgz24ys5P",
            "type": "RECTANGLE",
            "tags": [
                "counterclockwise",
                "counterclockwise_right"
            ],
            "boundingBox": {
                "height": 515.6434628326114,
                "width": 272.7921807317451,
                "left": 3014.019801980198,
                "top": 1240.8713886525372
            },
            "points": [
                {
                    "x": 3014.019801980198,
                    "y": 1240.8713886525372
                },
                {
                    "x": 3286.811982711943,
                    "y": 1240.8713886525372
                },
                {
                    "x": 3286.811982711943,
                    "y": 1756.5148514851485
                },
                {
                    "x": 3014.019801980198,
                    "y": 1756.5148514851485
                }
            ]
        },
        {
            "id": "ZWU-Svx9W",
            "type": "RECTANGLE",
            "tags": [
                "arrow_down"
            ],
            "boundingBox": {
                "height": 725.2277735341894,
                "width": 219.56450872137995,
                "left": 1244.1980705638923,
                "top": 635.4059913559715
            },
            "points": [
                {
                    "x": 1244.1980705638923,
                    "y": 635.4059913559715
                },
                {
                    "x": 1463.7625792852723,
                    "y": 635.4059913559715
                },
                {
                    "x": 1463.7625792852723,
                    "y": 1360.6337648901608
                },
                {
                    "x": 1244.1980705638923,
                    "y": 1360.6337648901608
                }
            ]
        },
        {
            "id": "7OX4GBQCz",
            "type": "RECTANGLE",
            "tags": [
                "arrow_up"
            ],
            "boundingBox": {
                "height": 555.5643310546875,
                "width": 226.21772025835395,
                "left": 2252.1982228496286,
                "top": 851.6435897373917
            },
            "points": [
                {
                    "x": 2252.1982228496286,
                    "y": 851.6435897373917
                },
                {
                    "x": 2478.4159431079825,
                    "y": 851.6435897373917
                },
                {
                    "x": 2478.4159431079825,
                    "y": 1407.2079207920792
                },
                {
                    "x": 2252.1982228496286,
                    "y": 1407.2079207920792
                }
            ]
        },
        {
            "id": "xdGeZnI3b",
            "type": "RECTANGLE",
            "tags": [
                "arrow_up"
            ],
            "boundingBox": {
                "height": 542.2575272663985,
                "width": 163.0096979424505,
                "left": 1453.7823812654703,
                "top": 1696.6336633663366
            },
            "points": [
                {
                    "x": 1453.7823812654703,
                    "y": 1696.6336633663366
                },
                {
                    "x": 1616.7920792079208,
                    "y": 1696.6336633663366
                },
                {
                    "x": 1616.7920792079208,
                    "y": 2238.8911906327353
                },
                {
                    "x": 1453.7823812654703,
                    "y": 2238.8911906327353
                }
            ]
        },
        {
            "id": "E-0rSRMw5",
            "type": "RECTANGLE",
            "tags": [
                "arrow_down"
            ],
            "boundingBox": {
                "height": 615.4455953163675,
                "width": 196.27712619894803,
                "left": 1979.4060421178838,
                "top": 1713.2673774945854
            },
            "points": [
                {
                    "x": 1979.4060421178838,
                    "y": 1713.2673774945854
                },
                {
                    "x": 2175.6831683168316,
                    "y": 1713.2673774945854
                },
                {
                    "x": 2175.6831683168316,
                    "y": 2328.712972810953
                },
                {
                    "x": 1979.4060421178838,
                    "y": 2328.712972810953
                }
            ]
        },
        {
            "id": "MWd9Yzhcj",
            "type": "RECTANGLE",
            "tags": [
                "arrow_down"
            ],
            "boundingBox": {
                "height": 495.6830667930074,
                "width": 182.97039855352722,
                "left": 2578.2179233060024,
                "top": 1719.9208936030323
            },
            "points": [
                {
                    "x": 2578.2179233060024,
                    "y": 1719.9208936030323
                },
                {
                    "x": 2761.18832185953,
                    "y": 1719.9208936030323
                },
                {
                    "x": 2761.18832185953,
                    "y": 2215.6039603960394
                },
                {
                    "x": 2578.2179233060024,
                    "y": 2215.6039603960394
                }
            ]
        }
    ],
    "version": "2.1.0"
}