{
    "asset": {
        "format": "jpg",
        "id": "e1479cc013e94317c8413cff99293092",
        "name": "20200331_155147.jpg",
        "path": "file:/home/oliv/Documents/mlHollf/TrainYourOwnYOLO/Data/Source_Images/Training_Images/20200331_155147.jpg",
        "size": {
            "width": 3024,
            "height": 3024
        },
        "state": 2,
        "type": 1
    },
    "regions": [
        {
            "id": "jDdgr3AoK",
            "type": "RECTANGLE",
            "tags": [
                "beam_90"
            ],
            "boundingBox": {
                "height": 1728,
                "width": 454.90909090909093,
                "left": 1307.4545454545455,
                "top": 546.5454545454546
            },
            "points": [
                {
                    "x": 1307.4545454545455,
                    "y": 546.5454545454546
                },
                {
                    "x": 1762.3636363636365,
                    "y": 546.5454545454546
                },
                {
                    "x": 1762.3636363636365,
                    "y": 2274.5454545454545
                },
                {
                    "x": 1307.4545454545455,
                    "y": 2274.5454545454545
                }
            ]
        },
        {
            "id": "Hvbo1ZWyt",
            "type": "RECTANGLE",
            "tags": [
                "support"
            ],
            "boundingBox": {
                "height": 333.8181818181818,
                "width": 304.3636363636364,
                "left": 1042.3636363636365,
                "top": 877.0909090909091
            },
            "points": [
                {
                    "x": 1042.3636363636365,
                    "y": 877.0909090909091
                },
                {
                    "x": 1346.7272727272727,
                    "y": 877.0909090909091
                },
                {
                    "x": 1346.7272727272727,
                    "y": 1210.909090909091
                },
                {
                    "x": 1042.3636363636365,
                    "y": 1210.909090909091
                }
            ]
        },
        {
            "id": "EKMdVujPy",
            "type": "RECTANGLE",
            "tags": [
                "roller_support"
            ],
            "boundingBox": {
                "height": 320.72727272727275,
                "width": 432,
                "left": 914.7272727272727,
                "top": 1600.3636363636365
            },
            "points": [
                {
                    "x": 914.7272727272727,
                    "y": 1600.3636363636365
                },
                {
                    "x": 1346.7272727272727,
                    "y": 1600.3636363636365
                },
                {
                    "x": 1346.7272727272727,
                    "y": 1921.0909090909092
                },
                {
                    "x": 914.7272727272727,
                    "y": 1921.0909090909092
                }
            ]
        },
        {
            "id": "A0epPLk0l",
            "type": "RECTANGLE",
            "tags": [
                "roller_support"
            ],
            "boundingBox": {
                "height": 307.6363636363637,
                "width": 432,
                "left": 1696.909090909091,
                "top": 1201.0909090909092
            },
            "points": [
                {
                    "x": 1696.909090909091,
                    "y": 1201.0909090909092
                },
                {
                    "x": 2128.909090909091,
                    "y": 1201.0909090909092
                },
                {
                    "x": 2128.909090909091,
                    "y": 1508.7272727272727
                },
                {
                    "x": 1696.909090909091,
                    "y": 1508.7272727272727
                }
            ]
        },
        {
            "id": "Hgd2gp98D",
            "type": "RECTANGLE",
            "tags": [
                "support"
            ],
            "boundingBox": {
                "height": 389.4545454545455,
                "width": 340.3636363636364,
                "left": 1654.3636363636365,
                "top": 513.8181818181819
            },
            "points": [
                {
                    "x": 1654.3636363636365,
                    "y": 513.8181818181819
                },
                {
                    "x": 1994.7272727272727,
                    "y": 513.8181818181819
                },
                {
                    "x": 1994.7272727272727,
                    "y": 903.2727272727274
                },
                {
                    "x": 1654.3636363636365,
                    "y": 903.2727272727274
                }
            ]
        },
        {
            "id": "yZ5Twp5JT",
            "type": "RECTANGLE",
            "tags": [
                "support"
            ],
            "boundingBox": {
                "height": 353.4545454545455,
                "width": 278.1818181818182,
                "left": 1723.0909090909092,
                "top": 1813.0909090909092
            },
            "points": [
                {
                    "x": 1723.0909090909092,
                    "y": 1813.0909090909092
                },
                {
                    "x": 2001.2727272727275,
                    "y": 1813.0909090909092
                },
                {
                    "x": 2001.2727272727275,
                    "y": 2166.5454545454545
                },
                {
                    "x": 1723.0909090909092,
                    "y": 2166.5454545454545
                }
            ]
        },
        {
            "id": "8k1G_5bUK",
            "type": "RECTANGLE",
            "tags": [
                "ground"
            ],
            "boundingBox": {
                "height": 438.54545454545456,
                "width": 130.9090909090909,
                "left": 1984.909090909091,
                "top": 1806.5454545454547
            },
            "points": [
                {
                    "x": 1984.909090909091,
                    "y": 1806.5454545454547
                },
                {
                    "x": 2115.818181818182,
                    "y": 1806.5454545454547
                },
                {
                    "x": 2115.818181818182,
                    "y": 2245.090909090909
                },
                {
                    "x": 1984.909090909091,
                    "y": 2245.090909090909
                }
            ]
        },
        {
            "id": "6WD57a2WB",
            "type": "RECTANGLE",
            "tags": [
                "ground"
            ],
            "boundingBox": {
                "height": 360,
                "width": 134.1818181818182,
                "left": 2089.636363636364,
                "top": 1168.3636363636365
            },
            "points": [
                {
                    "x": 2089.636363636364,
                    "y": 1168.3636363636365
                },
                {
                    "x": 2223.818181818182,
                    "y": 1168.3636363636365
                },
                {
                    "x": 2223.818181818182,
                    "y": 1528.3636363636365
                },
                {
                    "x": 2089.636363636364,
                    "y": 1528.3636363636365
                }
            ]
        },
        {
            "id": "CEl-5FVvF",
            "type": "RECTANGLE",
            "tags": [
                "ground"
            ],
            "boundingBox": {
                "height": 376.3636363636368,
                "width": 153.818181818182,
                "left": 782.1818181818182,
                "top": 1577.454545454546
            },
            "points": [
                {
                    "x": 782.1818181818182,
                    "y": 1577.454545454546
                },
                {
                    "x": 936.0000000000002,
                    "y": 1577.454545454546
                },
                {
                    "x": 936.0000000000002,
                    "y": 1953.8181818181827
                },
                {
                    "x": 782.1818181818182,
                    "y": 1953.8181818181827
                }
            ]
        }
    ],
    "version": "2.1.0"
}