{
    "asset": {
        "format": "jpg",
        "id": "f7531dfbbbee08f84d479acb6b9af7a9",
        "name": "20200331_161226.jpg",
        "path": "file:C:/Users/Benjamin/Desktop/gitRepos/mlHollf/Images/Benjamins%20Newest%20pictures/20200331_161226.jpg",
        "size": {
            "width": 4128,
            "height": 2322
        },
        "state": 2,
        "type": 1
    },
    "regions": [
        {
            "id": "f0dimDlvq",
            "type": "RECTANGLE",
            "tags": [
                "ground"
            ],
            "boundingBox": {
                "height": 939.5749091128463,
                "width": 266.94753873146186,
                "left": 260.48922789174543,
                "top": 664.4098443476064
            },
            "points": [
                {
                    "x": 260.48922789174543,
                    "y": 664.4098443476064
                },
                {
                    "x": 527.4367666232073,
                    "y": 664.4098443476064
                },
                {
                    "x": 527.4367666232073,
                    "y": 1603.9847534604528
                },
                {
                    "x": 260.48922789174543,
                    "y": 1603.9847534604528
                }
            ]
        },
        {
            "id": "EukQYvjbZ",
            "type": "RECTANGLE",
            "tags": [
                "support"
            ],
            "boundingBox": {
                "height": 555.9870727255837,
                "width": 460.69982034815024,
                "left": 475.769540799177,
                "top": 849.7388137852787
            },
            "points": [
                {
                    "x": 475.769540799177,
                    "y": 849.7388137852787
                },
                {
                    "x": 936.4693611473272,
                    "y": 849.7388137852787
                },
                {
                    "x": 936.4693611473272,
                    "y": 1405.7258865108624
                },
                {
                    "x": 475.769540799177,
                    "y": 1405.7258865108624
                }
            ]
        },
        {
            "id": "VFb4KDdrw",
            "type": "RECTANGLE",
            "tags": [
                "clockwise",
                "clockwise_bottom"
            ],
            "boundingBox": {
                "height": 258.59860788863114,
                "width": 434.86616637467404,
                "left": 996.7479144597457,
                "top": 586.8302948635305
            },
            "points": [
                {
                    "x": 996.7479144597457,
                    "y": 586.8302948635305
                },
                {
                    "x": 1431.6140808344198,
                    "y": 586.8302948635305
                },
                {
                    "x": 1431.6140808344198,
                    "y": 845.4289027521617
                },
                {
                    "x": 996.7479144597457,
                    "y": 845.4289027521617
                }
            ]
        },
        {
            "id": "B7JhwCa5-",
            "type": "RECTANGLE",
            "tags": [
                "counterclockwise",
                "counterclockwise_top"
            ],
            "boundingBox": {
                "height": 232.73881286479482,
                "width": 400.42151340449806,
                "left": 1552.1710232134126,
                "top": 668.7197553807234
            },
            "points": [
                {
                    "x": 1552.1710232134126,
                    "y": 668.7197553807234
                },
                {
                    "x": 1952.5925366179106,
                    "y": 668.7197553807234
                },
                {
                    "x": 1952.5925366179106,
                    "y": 901.4585682455183
                },
                {
                    "x": 1552.1710232134126,
                    "y": 901.4585682455183
                }
            ]
        },
        {
            "id": "TYlW-7PoV",
            "type": "RECTANGLE",
            "tags": [
                "counterclockwise",
                "counterclockwise_top"
            ],
            "boundingBox": {
                "height": 267.2185943674322,
                "width": 396.1156443529987,
                "left": 2086.0664291680246,
                "top": 655.7898578688054
            },
            "points": [
                {
                    "x": 2086.0664291680246,
                    "y": 655.7898578688054
                },
                {
                    "x": 2482.1820735210235,
                    "y": 655.7898578688054
                },
                {
                    "x": 2482.1820735210235,
                    "y": 923.0084522362375
                },
                {
                    "x": 2086.0664291680246,
                    "y": 923.0084522362375
                }
            ]
        },
        {
            "id": "yyERb6VbS",
            "type": "RECTANGLE",
            "tags": [
                "clockwise",
                "clockwise_bottom"
            ],
            "boundingBox": {
                "height": 228.42873741911072,
                "width": 421.9495446952412,
                "left": 2594.12777053455,
                "top": 578.2103083847294
            },
            "points": [
                {
                    "x": 2594.12777053455,
                    "y": 578.2103083847294
                },
                {
                    "x": 3016.077315229791,
                    "y": 578.2103083847294
                },
                {
                    "x": 3016.077315229791,
                    "y": 806.6390458038402
                },
                {
                    "x": 2594.12777053455,
                    "y": 806.6390458038402
                }
            ]
        },
        {
            "id": "HHKlAM9Bt",
            "type": "RECTANGLE",
            "tags": [
                "clockwise",
                "clockwise_top"
            ],
            "boundingBox": {
                "height": 254.28869685551408,
                "width": 430.5606258148631,
                "left": 3196.9126466753582,
                "top": 604.0701034085657
            },
            "points": [
                {
                    "x": 3196.9126466753582,
                    "y": 604.0701034085657
                },
                {
                    "x": 3627.4732724902215,
                    "y": 604.0701034085657
                },
                {
                    "x": 3627.4732724902215,
                    "y": 858.3588002640798
                },
                {
                    "x": 3196.9126466753582,
                    "y": 858.3588002640798
                }
            ]
        },
        {
            "id": "B2YM1V01P",
            "type": "RECTANGLE",
            "tags": [
                "arrow_up"
            ],
            "boundingBox": {
                "height": 530.1272777017474,
                "width": 193.75228161668838,
                "left": 2133.428032309322,
                "top": 1190.2270466036698
            },
            "points": [
                {
                    "x": 2133.428032309322,
                    "y": 1190.2270466036698
                },
                {
                    "x": 2327.1803139260105,
                    "y": 1190.2270466036698
                },
                {
                    "x": 2327.1803139260105,
                    "y": 1720.354324305417
                },
                {
                    "x": 2133.428032309322,
                    "y": 1720.354324305417
                }
            ]
        },
        {
            "id": "FPp7GdqGb",
            "type": "RECTANGLE",
            "tags": [
                "arrow_up"
            ],
            "boundingBox": {
                "height": 353.41829474287636,
                "width": 180.83549569141132,
                "left": 1689.9504563233377,
                "top": 1194.5369576367868
            },
            "points": [
                {
                    "x": 1689.9504563233377,
                    "y": 1194.5369576367868
                },
                {
                    "x": 1870.785952014749,
                    "y": 1194.5369576367868
                },
                {
                    "x": 1870.785952014749,
                    "y": 1547.955252379663
                },
                {
                    "x": 1689.9504563233377,
                    "y": 1547.955252379663
                }
            ]
        },
        {
            "id": "bL363FRoT",
            "type": "RECTANGLE",
            "tags": [
                "arrow_up"
            ],
            "boundingBox": {
                "height": 728.3859802387707,
                "width": 129.16818774445892,
                "left": 1349.8076604771022,
                "top": 1203.156944115588
            },
            "points": [
                {
                    "x": 1349.8076604771022,
                    "y": 1203.156944115588
                },
                {
                    "x": 1478.9758482215611,
                    "y": 1203.156944115588
                },
                {
                    "x": 1478.9758482215611,
                    "y": 1931.5429243543585
                },
                {
                    "x": 1349.8076604771022,
                    "y": 1931.5429243543585
                }
            ]
        },
        {
            "id": "V4pggtZRp",
            "type": "RECTANGLE",
            "tags": [
                "arrow_up"
            ],
            "boundingBox": {
                "height": 560.2969837587008,
                "width": 232.50280363836376,
                "left": 1022.5814863102999,
                "top": 1194.5369576367868
            },
            "points": [
                {
                    "x": 1022.5814863102999,
                    "y": 1194.5369576367868
                },
                {
                    "x": 1255.0842899486636,
                    "y": 1194.5369576367868
                },
                {
                    "x": 1255.0842899486636,
                    "y": 1754.8339413954875
                },
                {
                    "x": 1022.5814863102999,
                    "y": 1754.8339413954875
                }
            ]
        },
        {
            "id": "7-M49K9_f",
            "type": "RECTANGLE",
            "tags": [
                "beam"
            ],
            "boundingBox": {
                "height": 241.35879934359593,
                "width": 2699.6151567083602,
                "left": 927.8581157818611,
                "top": 970.4181312507931
            },
            "points": [
                {
                    "x": 927.8581157818611,
                    "y": 970.4181312507931
                },
                {
                    "x": 3627.4732724902215,
                    "y": 970.4181312507931
                },
                {
                    "x": 3627.4732724902215,
                    "y": 1211.7769305943891
                },
                {
                    "x": 927.8581157818611,
                    "y": 1211.7769305943891
                }
            ]
        }
    ],
    "version": "2.1.0"
}